{"problem_instance_uuid": "22676ba7-4107-47fd-be97-fba7fe83ed9f", "$schema": "https://raw.githubusercontent.com/jp7745/qb-file-schemas/main/schemas/problem_instance.schema.0.0.1.json", "problem_type": "GSEE", "application_domain": "QC", "calendar_due_date": null, "creation_timestamp": "2023-10-16T19:36:39.363130Z", "status": "in_force", "superseded_by": null, "contact_info": [{"name": "BOBQAT Team", "email": "bobqat@l3harris.com", "institution": "L3Harris Technologies, Inc", "other_info": {"website": "www.l3harris.com"}}, {"name": "Zapata AI", "email": "bobqat@zapatacomputing.com", "institution": "Zapata AI", "other_info": {"website": "https://zapata.ai/"}}], "short_name": "NH3_family", "instance_data": [{"instance_data_object_uuid": "88888888-4444-4444-4444-121212121212", "instance_data_object_url": "https://this-example-does-not-work-yet", "instance_data_checksum_type": "sha1sum", "instance_data_checksum": "4040404040404040404040404040404040404040", "independent_parameters": {"bond_length": 1.0, "basis": "sto-6g"}, "features": {"software_used": "CHEMISTRY_SOFTWARE_PLACEHOLDER", "molecule_name": "NH3", "basis_set": "sto-6g", "charge": "0", "multiplicity": "1", "avas_minao": "STO-3G", "method_type": "DMRG", "geometry": [{"element": "N", "coodinates": [0.0, 0.30014, -1e-05]}, {"element": "H", "coodinates": [-0.0, -0.19902, 0.8646]}, {"element": "H", "coodinates": [0.0, -0.19894, -0.8646]}, {"element": "H", "coodinates": [0.0, 1.29851, 1e-05]}], "avas_atomic_orbitals": [{"element": "H", "orbital": "1s"}, {"element": "N", "orbital": "2s"}, {"element": "N", "orbital": "2p"}]}, "requirements": {"time_limit_seconds": 86400, "accuracy": 1.0, "enery_units": "millihartree"}}, {"instance_data_object_uuid": "88888888-4444-4444-4444-121212121212", "instance_data_object_url": "https://this-example-does-not-work-yet", "instance_data_checksum_type": "sha1sum", "instance_data_checksum": "4040404040404040404040404040404040404040", "independent_parameters": {"bond_length": 1.0, "basis": "cc-pvtz"}, "features": {"software_used": "CHEMISTRY_SOFTWARE_PLACEHOLDER", "molecule_name": "NH3", "basis_set": "cc-pvtz", "charge": "0", "multiplicity": "1", "avas_minao": "STO-3G", "method_type": "DMRG", "geometry": [{"element": "N", "coodinates": [0.0, 0.30014, -1e-05]}, {"element": "H", "coodinates": [-0.0, -0.19902, 0.8646]}, {"element": "H", "coodinates": [0.0, -0.19894, -0.8646]}, {"element": "H", "coodinates": [0.0, 1.29851, 1e-05]}], "avas_atomic_orbitals": [{"element": "H", "orbital": "1s"}, {"element": "N", "orbital": "2s"}, {"element": "N", "orbital": "2p"}]}, "requirements": {"time_limit_seconds": 86400, "accuracy": 1.0, "enery_units": "millihartree"}}, {"instance_data_object_uuid": "88888888-4444-4444-4444-121212121212", "instance_data_object_url": "https://this-example-does-not-work-yet", "instance_data_checksum_type": "sha1sum", "instance_data_checksum": "4040404040404040404040404040404040404040", "independent_parameters": {"bond_length": 1.5, "basis": "sto-6g"}, "features": {"software_used": "CHEMISTRY_SOFTWARE_PLACEHOLDER", "molecule_name": "NH3", "basis_set": "sto-6g", "charge": "0", "multiplicity": "1", "avas_minao": "STO-3G", "method_type": "DMRG", "geometry": [{"element": "N", "coodinates": [0.0, 0.45021, -2e-05]}, {"element": "H", "coodinates": [-0.0, -0.29852, 1.2969]}, {"element": "H", "coodinates": [0.0, -0.29842, -1.2969]}, {"element": "H", "coodinates": [0.0, 1.94776, 1e-05]}], "avas_atomic_orbitals": [{"element": "H", "orbital": "1s"}, {"element": "N", "orbital": "2s"}, {"element": "N", "orbital": "2p"}]}, "requirements": {"time_limit_seconds": 86400, "accuracy": 1.0, "enery_units": "millihartree"}}, {"instance_data_object_uuid": "88888888-4444-4444-4444-121212121212", "instance_data_object_url": "https://this-example-does-not-work-yet", "instance_data_checksum_type": "sha1sum", "instance_data_checksum": "4040404040404040404040404040404040404040", "independent_parameters": {"bond_length": 1.5, "basis": "cc-pvtz"}, "features": {"software_used": "CHEMISTRY_SOFTWARE_PLACEHOLDER", "molecule_name": "NH3", "basis_set": "cc-pvtz", "charge": "0", "multiplicity": "1", "avas_minao": "STO-3G", "method_type": "DMRG", "geometry": [{"element": "N", "coodinates": [0.0, 0.45021, -2e-05]}, {"element": "H", "coodinates": [-0.0, -0.29852, 1.2969]}, {"element": "H", "coodinates": [0.0, -0.29842, -1.2969]}, {"element": "H", "coodinates": [0.0, 1.94776, 1e-05]}], "avas_atomic_orbitals": [{"element": "H", "orbital": "1s"}, {"element": "N", "orbital": "2s"}, {"element": "N", "orbital": "2p"}]}, "requirements": {"time_limit_seconds": 86400, "accuracy": 1.0, "enery_units": "millihartree"}}, {"instance_data_object_uuid": "88888888-4444-4444-4444-121212121212", "instance_data_object_url": "https://this-example-does-not-work-yet", "instance_data_checksum_type": "sha1sum", "instance_data_checksum": "4040404040404040404040404040404040404040", "independent_parameters": {"bond_length": 2.0, "basis": "sto-6g"}, "features": {"software_used": "CHEMISTRY_SOFTWARE_PLACEHOLDER", "molecule_name": "NH3", "basis_set": "sto-6g", "charge": "0", "multiplicity": "1", "avas_minao": "STO-3G", "method_type": "DMRG", "geometry": [{"element": "N", "coodinates": [0.0, 0.60029, -2e-05]}, {"element": "H", "coodinates": [-0.0, -0.39803, 1.7292]}, {"element": "H", "coodinates": [0.0, -0.39789, -1.72921]}, {"element": "H", "coodinates": [0.0, 2.59701, 1e-05]}], "avas_atomic_orbitals": [{"element": "H", "orbital": "1s"}, {"element": "N", "orbital": "2s"}, {"element": "N", "orbital": "2p"}]}, "requirements": {"time_limit_seconds": 86400, "accuracy": 1.0, "enery_units": "millihartree"}}, {"instance_data_object_uuid": "88888888-4444-4444-4444-121212121212", "instance_data_object_url": "https://this-example-does-not-work-yet", "instance_data_checksum_type": "sha1sum", "instance_data_checksum": "4040404040404040404040404040404040404040", "independent_parameters": {"bond_length": 2.0, "basis": "cc-pvtz"}, "features": {"software_used": "CHEMISTRY_SOFTWARE_PLACEHOLDER", "molecule_name": "NH3", "basis_set": "cc-pvtz", "charge": "0", "multiplicity": "1", "avas_minao": "STO-3G", "method_type": "DMRG", "geometry": [{"element": "N", "coodinates": [0.0, 0.60029, -2e-05]}, {"element": "H", "coodinates": [-0.0, -0.39803, 1.7292]}, {"element": "H", "coodinates": [0.0, -0.39789, -1.72921]}, {"element": "H", "coodinates": [0.0, 2.59701, 1e-05]}], "avas_atomic_orbitals": [{"element": "H", "orbital": "1s"}, {"element": "N", "orbital": "2s"}, {"element": "N", "orbital": "2p"}]}, "requirements": {"time_limit_seconds": 86400, "accuracy": 1.0, "enery_units": "millihartree"}}]}